CHANGES.txt
LICENCE.txt
MANIFEST.in
README.rst
setup.py
django_webperf.egg-info/PKG-INFO
django_webperf.egg-info/SOURCES.txt
django_webperf.egg-info/dependency_links.txt
django_webperf.egg-info/requires.txt
django_webperf.egg-info/top_level.txt
tests/__init__.py
tests/models.py
tests/tests.py
web_performance/__init__.py
web_performance/models.py
web_performance/storage.py