Metadata-Version: 1.0
Name: django-webperf
Version: 0.1
Summary: A collection of stuff to improve django web performance.
Home-page: https://github.com/coagulant/django-webperf
Author: Ilya Baryshev
Author-email: baryshev@gmail.com
License: MIT
Platform: UNKNOWN
Classifier: Development Status :: 3 - Alpha
Classifier: Framework :: Django
Classifier: Intended Audience :: Developers
Classifier: License :: OSI Approved :: MIT License
Classifier: Operating System :: OS Independent
Classifier: Programming Language :: Python
